Metadata-Version: 1.1
Name: sfml
Version: 2.3.2.dev1
Summary: Python bindings for SFML
Home-page: http://python-sfml.org
Author: Jonathan de Wachter
Author-email: dewachter.jonathan@gmail.com
License: UNKNOWN
Keywords: sfml SFML simple fast multimedia system window graphics audio network pySFML PySFML python-sfml
Platform: UNKNOWN
Classifier: Development Status :: 5 - Production/Stable
Classifier: Intended Audience :: Developers
Classifier: License :: OSI Approved :: zlib/libpng License
Classifier: Operating System :: OS Independent
Classifier: Programming Language :: Python :: 2
Classifier: Programming Language :: Python :: 3
Classifier: Programming Language :: Cython
Classifier: Programming Language :: C++
Classifier: Programming Language :: Python
Classifier: Programming Language :: Python :: Implementation :: CPython
Classifier: Topic :: Games/Entertainment
Classifier: Topic :: Multimedia
Classifier: Topic :: Software Development :: Libraries :: Python Modules
